geoarrow/pandas/__init__.py
geoarrow/pandas/lib.py
geoarrow_pandas-0.1.1.dist-info/METADATA
geoarrow_pandas-0.1.1.dist-info/WHEEL
geoarrow_pandas-0.1.1.dist-info/top_level.txt
geoarrow_pandas-0.1.1.dist-info/RECORD
